shuttle/cli.py
shuttle/constants.py
shuttle/flash.py
shuttle/prodtest.py
shuttle/serial_client.py
shuttle/timo.py
shuttle/firmware/__init__.py
shuttle/firmware/esp32c5/__init__.py
shuttle/firmware/esp32c5/boot_app0.bin
shuttle/firmware/esp32c5/devboard.ino.bin
shuttle/firmware/esp32c5/devboard.ino.bootloader.bin
shuttle/firmware/esp32c5/devboard.ino.partitions.bin
shuttle/firmware/esp32c5/manifest.json
lr_shuttle-0.2.9.dist-info/METADATA
lr_shuttle-0.2.9.dist-info/WHEEL
lr_shuttle-0.2.9.dist-info/entry_points.txt
lr_shuttle-0.2.9.dist-info/top_level.txt
lr_shuttle-0.2.9.dist-info/RECORD
