Metadata-Version: 2.4
Name: lr-shuttle
Version: 0.2.9
Summary: CLI and Python client for host-side of json based serial communication with embedded device bridge.
Author-email: Jonas Estberger <jonas.estberger@lumenradio.com>
License: MIT
Keywords: CLI
Classifier: Programming Language :: Python :: 3
Classifier: License :: OSI Approved :: MIT License
Classifier: Operating System :: OS Independent
Requires-Python: >=3.11
Requires-Dist: rich>=13.7
Requires-Dist: pydantic>=2.8
Requires-Dist: typer>=0.12
Requires-Dist: pyserial>=3.5
Requires-Dist: esptool>=4.7
Provides-Extra: dev
Requires-Dist: build>=1.2.1; extra == "dev"
Requires-Dist: twine>=5.1.1; extra == "dev"
Requires-Dist: wheel; extra == "dev"
Requires-Dist: pytest>=8.4.2; extra == "dev"
Requires-Dist: black>=25.9.0; extra == "dev"
Requires-Dist: pytest-html; extra == "dev"
Requires-Dist: pytest-cov; extra == "dev"
